eyeseg/__init__.py
eyeseg/io_utils/__init__.py
eyeseg/io_utils/input_pipe.py
eyeseg/io_utils/losses.py
eyeseg/io_utils/metrics.py
eyeseg/io_utils/test.ipynb
eyeseg/io_utils/utils.py
eyeseg/models/__init__.py
eyeseg/models/custom_unet.py
eyeseg/models/feature_refinement_net.py
eyeseg/models/feature_refinement_net_he.py
eyeseg/models/multiscale_gated_densenet.py
eyeseg/models/parts.py
eyeseg/models/utils.py
eyeseg/models/vanilla_unet.py
eyeseg/models/weights/1zc44dxo/__init__.py
eyeseg/models/weights/1zc44dxo/config.yaml
eyeseg/models/weights/1zc44dxo/model-best.h5
eyeseg/models/weights/2c41ukad/__init__.py
eyeseg/models/weights/2c41ukad/config.yaml
eyeseg/models/weights/2c41ukad/model-best.h5
eyeseg/models/weights/3avqygsi/__init__.py
eyeseg/models/weights/3avqygsi/config.yaml
eyeseg/models/weights/3avqygsi/model-best.h5
eyeseg/models/weights/__init__.py
eyeseg/scripts/__init__.py
eyeseg/scripts/commands/__init__.py
eyeseg/scripts/commands/check.py
eyeseg/scripts/commands/evaluate.py
eyeseg/scripts/commands/plot_bscans.py
eyeseg/scripts/commands/plot_data.py
eyeseg/scripts/commands/plot_enface.py
eyeseg/scripts/commands/quantify.py
eyeseg/scripts/commands/segment.py
eyeseg/scripts/commands/train.py
eyeseg/scripts/main.py
eyeseg/scripts/utils.py
eyesegpy-1.0.2.dist-info/LICENSE
eyesegpy-1.0.2.dist-info/METADATA
eyesegpy-1.0.2.dist-info/WHEEL
eyesegpy-1.0.2.dist-info/entry_points.txt
eyesegpy-1.0.2.dist-info/RECORD
