Metadata-Version: 2.1
Name: eyesegpy
Version: 1.0.2
Summary: A python command line tool to segment drusen and retinal layers in OCT images.
Home-page: https://github.com/MedVisBonn/eyeseg
Keywords: ophthalmology,oct,segmentation,spectralis,drusen,retina
Author: Olivier Morelle
Author-email: oli4morelle@gmail.com
Requires-Python: >=3.8,<3.11
Classifier: Development Status :: 4 - Beta
Classifier: Intended Audience :: Developers
Classifier: Intended Audience :: Healthcare Industry
Classifier: Intended Audience :: Science/Research
Classifier: License :: OSI Approved :: MIT License
Classifier: Natural Language :: English
Classifier: Operating System :: OS Independent
Classifier: Programming Language :: Python :: 3
Classifier: Programming Language :: Python :: 3.8
Classifier: Programming Language :: Python :: 3.9
Classifier: Programming Language :: Python :: 3.10
Classifier: Programming Language :: Python :: 3 :: Only
Classifier: Topic :: Scientific/Engineering :: Image Processing
Classifier: Topic :: Scientific/Engineering :: Medical Science Apps.
Classifier: Topic :: Scientific/Engineering :: Visualization
Requires-Dist: PyYAML (>=6.0,<7.0)
Requires-Dist: click (>=8.1.3,<9.0.0)
Requires-Dist: eyepie (>=0.11.3,<0.12.0)
Requires-Dist: pandas (>=1.5.2,<2.0.0)
Requires-Dist: tensorflow (==2.11.0)
Requires-Dist: tensorflow-addons (>=0.18.0,<0.19.0)
Requires-Dist: tensorflow-probability (>=0.18.0,<0.19.0)
Requires-Dist: tqdm (>=4.64.1,<5.0.0)
Project-URL: Repository, https://github.com/MedVisBonn/eyeseg
